function_calling/__init__.py
function_calling/api.py
function_calling/models.py
openai_function_calling_aeolin-0.0.7.dist-info/LICENSE
openai_function_calling_aeolin-0.0.7.dist-info/METADATA
openai_function_calling_aeolin-0.0.7.dist-info/WHEEL
openai_function_calling_aeolin-0.0.7.dist-info/top_level.txt
openai_function_calling_aeolin-0.0.7.dist-info/RECORD
